CHANGELOG.md
LICENSE
netprot/__init__.py
netprot/netprot.py
netprot-0.1.2.dist-info/LICENSE
netprot-0.1.2.dist-info/WHEEL
netprot-0.1.2.dist-info/METADATA
netprot-0.1.2.dist-info/RECORD
