Metadata-Version: 2.1
Name: netprot
Version: 0.1.2
Summary: A system-indipendent network protocol manipulation and evaluation library.
Home-page: https://github.com/lvrfrc87/netprot
License: GPL-3.0-or-later
Keywords: networking,automation,network
Author: Federico Olivieri
Author-email: lvrfrc87@gmail.com
Requires-Python: >=3.7,<4.0
Classifier: License :: OSI Approved :: GNU General Public License v3 or later (GPLv3+)
Classifier: Programming Language :: Python :: 3
Classifier: Programming Language :: Python :: 3.10
Classifier: Programming Language :: Python :: 3.6
Classifier: Programming Language :: Python :: 3.7
Classifier: Programming Language :: Python :: 3.8
Classifier: Programming Language :: Python :: 3.9
Project-URL: Repository, https://github.com/lvrfrc87/netprot
